chrono/__init__.py
shodan_chrono-0.1.0.dist-info/WHEEL
shodan_chrono-0.1.0.dist-info/METADATA
shodan_chrono-0.1.0.dist-info/RECORD
