Metadata-Version: 2.1
Name: shodan-chrono
Version: 0.1.0
Summary: Create a progress bar that you can view on chrono.shodan.io
Home-page: https://chrono.shodan.io
Author: John Matherly
Author-email: jmath@shodan.io
Requires-Python: >=3.6
Classifier: Programming Language :: Python :: 3
Classifier: Programming Language :: Python :: 3.6
Classifier: Programming Language :: Python :: 3.7
Classifier: Programming Language :: Python :: 3.8
Classifier: Programming Language :: Python :: 3.9
Requires-Dist: construct (>=2.10.68,<3.0.0)
Requires-Dist: shodan (>=1.27.0,<2.0.0)
Project-URL: Repository, https://gitlab.com/shodan-public/chrono-clients
